[
  {
    "Id": 1,
    "StartOfLocation": "2023-12-16T14:15:00",
    "LocationDuration": 5,
    "IsReturned": false,
    "BoatId": 1,
    "MemberId": 0
  },
  {
    "Id": 2,
    "StartOfLocation": "2023-12-30T19:37:00",
    "LocationDuration": 1,
    "IsReturned": false,
    "BoatId": 1,
    "MemberId": 0
  },
  {
    "Id": 3,
    "StartOfLocation": "2023-12-08T10:00:00",
    "LocationDuration": 4,
    "IsReturned": false,
    "BoatId": 2,
    "MemberId": 0
  },
  {
    "Id": 4,
    "StartOfLocation": "2023-12-13T11:23:00",
    "LocationDuration": 2,
    "IsReturned": false,
    "BoatId": 2,
    "MemberId": 0
  },
  {
    "Id": 5,
    "StartOfLocation": "2023-12-21T09:30:00",
    "LocationDuration": 5,
    "IsReturned": false,
    "BoatId": 1,
    "MemberId": 1
  }
]